catshand/__init__.py
catshand/audacitytool.py
catshand/dash.py
catshand/main.py
catshand/openai.py
catshand/pipefunc.py
catshand/postproc.py
catshand/utility.py
catshand/webtool.py
catshand/config/audt_config.json
catshand/config/hosts_dict.json
catshand/doc/manuals.md
catshand/fig/audacity_preference.png
catshand/fig/screen.png
catshand/fig/screen_02.png
catshand/tools/__init__.py
catshand/tools/app.py
catshand/tools/audacitypipe.py
catshand/tools/audacitypipe_prjpre.py
catshand/tools/audio2wav.py
catshand/tools/audiosplit.py
catshand/tools/audmerger.py
catshand/tools/cleanvoice.py
catshand/tools/linkparser.py
catshand/tools/prjinit.py
catshand/tools/prjsummary.py
catshand/tools/silrm.py
catshand/tools/trackmerger.py
catshand/tools/deprecated/highlight.py
catshand/tools/deprecated/prjpost.py
catshand-0.3.6.dist-info/LICENSE
catshand-0.3.6.dist-info/METADATA
catshand-0.3.6.dist-info/WHEEL
catshand-0.3.6.dist-info/entry_points.txt
catshand-0.3.6.dist-info/top_level.txt
catshand-0.3.6.dist-info/RECORD
