Metadata-Version: 2.1
Name: catshand
Version: 0.3.6
Summary: Tools for Podcast editing
Author-email: Mike Chien-Cheng Shih <m.cc.shih@gmail.com>
License: BSD 2-clause
Project-URL: Homepage, https://github.com/eufmike/catshand
Classifier: Development Status :: 1 - Planning
Classifier: Intended Audience :: Science/Research
Classifier: License :: OSI Approved :: BSD License
Classifier: Operating System :: POSIX :: Linux
Classifier: Programming Language :: Python :: 2
Classifier: Programming Language :: Python :: 2.7
Classifier: Programming Language :: Python :: 3
Classifier: Programming Language :: Python :: 3.4
Classifier: Programming Language :: Python :: 3.5
Requires-Python: >=3.9
License-File: LICENSE
Requires-Dist: jupyterlab >=4.1.2
Requires-Dist: matplotlib >=3.8.3
Requires-Dist: numpy >=1.26.4
Requires-Dist: pandas >=2.2.1
Requires-Dist: openai >=1.13.3
Requires-Dist: librosa >=0.10.0
Requires-Dist: click >=8.1.3
Requires-Dist: fuzzywuzzy >=0.18.0
Requires-Dist: pydub >=0.25.1
Requires-Dist: tqdm >=4.66.2
Requires-Dist: lxml >=5.1.0
Requires-Dist: dash >=2.16.0
Requires-Dist: tiktoken >=0.6.0
Requires-Dist: OpenCC ==1.1.7
Requires-Dist: noisereduce ==2.0.1
Requires-Dist: fake-useragent >=1.4.0
Requires-Dist: dash-bootstrap-components ==1.4.1
Requires-Dist: python-Levenshtein ==0.25.0
Provides-Extra: dev
Requires-Dist: black ; extra == 'dev'
Requires-Dist: bumpver ; extra == 'dev'
Requires-Dist: isort ; extra == 'dev'
Requires-Dist: pip-tools ; extra == 'dev'
Requires-Dist: pytest ; extra == 'dev'
Provides-Extra: win
Requires-Dist: pywin32 ; extra == 'win'
Requires-Dist: pywinpty ; extra == 'win'
